docx2markdown_custom/__init__.py
docx2markdown_custom-1.0.0.dist-info/METADATA
docx2markdown_custom-1.0.0.dist-info/WHEEL
docx2markdown_custom-1.0.0.dist-info/top_level.txt
docx2markdown_custom-1.0.0.dist-info/RECORD
